django_model_privacy_mixin/__init__.py
django_model_privacy_mixin-0.4.dist-info/LICENSE.md
django_model_privacy_mixin-0.4.dist-info/METADATA
django_model_privacy_mixin-0.4.dist-info/WHEEL
django_model_privacy_mixin-0.4.dist-info/top_level.txt
django_model_privacy_mixin-0.4.dist-info/RECORD
