Metadata-Version: 2.1
Name: django-model-privacy-mixin
Version: 0.4
Summary: Django Model MixIn providing flexible field privacy control
Home-page: https://github.com/bernd-wechner/django-model-privacy-mixin
Author: Bernd Wechner
Author-email: bwechner@yahoo.com
Project-URL: Bug Tracker, https://github.com/bernd-wechner/django-model-privacy-mixin/issues
Classifier: Programming Language :: Python :: 3
Classifier: License :: Freely Distributable
Classifier: Operating System :: OS Independent
Classifier: Development Status :: 4 - Beta
Classifier: Framework :: Django :: 4.0
Classifier: Intended Audience :: System Administrators
Classifier: Topic :: Software Development :: Libraries :: Python Modules
Requires-Python: >=3.6
License-File: LICENSE.md
Requires-Dist: django-crequest
Requires-Dist: django-bitfield (>=2.0.1)
